{"properties": [
  {
    "name": "grpc.server.port",
    "type": "java.lang.String",
    "description": "A description for 'grpc.server.port'"
  },
  {
    "name": "kafka.topics.payment-request",
    "type": "java.lang.String",
    "description": "A description for 'kafka.topics.payment-request-topic'"
  },
  {
    "name": "zalopay.callback.url",
    "type": "java.lang.String",
    "description": "A description for 'zalopay.callback.url'"
  },
  {
    "name": "kafka.group-id",
    "type": "java.lang.String",
    "description": "A description for 'kafka.group-id'"
  }
]}